README.rst
rex.py
setup.py
python_rex.egg-info/PKG-INFO
python_rex.egg-info/SOURCES.txt
python_rex.egg-info/dependency_links.txt
python_rex.egg-info/top_level.txt