Metadata-Version: 1.1
Name: python-rex
Version: 0.3.1
Summary: Python regular expressions for humans
Home-page: https://github.com/cypreess/python-rex
Author: Krzysztof Dorosz
Author-email: cypreess@gmail.com
License: MIT
Platform: UNKNOWN
Classifier: Development Status :: 4 - Beta
Classifier: Intended Audience :: Developers
Classifier: Natural Language :: English
Classifier: License :: OSI Approved :: MIT License
Classifier: Programming Language :: Python
Classifier: Programming Language :: Python :: 2.7
